ALU_32_Bit.v
module ALU_32_Bit #(
    parameter WIDTH = 32,
    parameter NUM_OPS = 16
)

(
    input wire [WIDTH-1:0] a,
    input wire [WIDTH-1:0] b,
    input wire [$clog2(NUM_OPS):0] op_select, // rounding 
    output reg [2*WIDTH-1:0] result
);

localparam ADD = 0;
localparam SUB = 1;
localparam AND = 2;
localparam OR = 3; 
localparam NAND = 4;
localparam NOR = 5;
localparam XOR = 6;
localparam XNOR = 7;
localparam MUL = 8;
localparam DIV = 9;

// what about left right shift, greater equal to comparison, multiplication division

    always @(*) begin
        case (op_select)
            ADD: result = a + b; // Addition
            SUB: result = a - b; // Subtraction
            AND: result = a & b; // Bitwise AND
            OR: result = a | b; // Bitwise OR
            NAND: result = ~(a & b); // Bitwise NAND
            NOR: result = ~(a | b); // Bitwise NOR
            XOR: result = a ^ b; // Bitwise XOR
            XNOR: result= ~(a ^ b); // Bitwise XNOR
            MUL: result = a * b; // Bitwise MUL 
            DIV: result = a / b; // Bitwise DIV
            default: result = 0;      // Default case
        endcase
    end

    
endmodule

ALU_32_Bit_Testbench.v
`timescale 1ps/1ps
`include "ALU_32_Bit.v"
 
module ALU_32_Bit_Testbench;
 
    reg [15:0] a, b;
    reg [3:0] op_select;
    wire [31:0] result;
 
 //
    ALU_32_Bit #(.WIDTH(16), .NUM_OPS(8)) 
    
    alu_16_bit_inst ( 
        // in reference to one copy of the design that we are testing
        .a(a),
        .b(b),
        .op_select(op_select),
        .result(result)
    );
 
    initial begin
        // Test Addition
        a = 16'd5; b = 16'h3; op_select = 3'b000;
        #10; $display("ADD: %h + %h = %h", a, b, result); 
 
        // Test Subtraction
        a = 16'd5; b = 16'd3; op_select = 3'b001;
        #10; $display("SUB: %h - %h = %h", a, b, result);
 
        // Test Bitwise AND
        a = 16'hFFFF; b = 16'h0001; op_select = 3'b010;
        #10; $display("AND: %h & %h = %h", a, b, result);
 
        // Test Bitwise OR
        a = 16'hF0F0; b = 16'h0000; op_select = 3'b011;
        #10; $display("OR: %h | %h = %h", a, b, result);

        // Test Bitwise NAND
        a = 16'hFFFF; b = 16'h00FF; op_select = 3'b100;
        #10; $display("NAND: ~(%h & %h) = %h", a, b, result);

        // Test Bitwise NOR
        a = 16'h0000; b = 16'h00FF; op_select = 3'b101;
        #10; $display("NOR: ~(%h | %h) = %h", a, b, result);

        // Test Bitwise XOR
        a = 16'hAAAA; b = 16'h5555; op_select = 3'b110;
        #10; $display("XOR: %h ^ %h = %h", a, b, result);

        // Test Bitwise XNOR
        a = 16'hAAAA; b = 16'h5555; op_select = 3'b111;
        #10; $display("XNOR: ~(%h ^ %h) = %h", a, b, result);
 
        $finish;
    end
 
    initial begin
        $dumpfile("My_ALU_Test.vcd"); 
        $dumpvars(0, ALU_32_Bit_Testbench); // 0 is to include all instances (dumping waves)
    end
 
endmodule

My_ALU_Test.vcd
$date
	Thu Aug 21 19:06:51 2025
$end
$version
	Icarus Verilog
$end
$timescale
	1ps
$end
$scope module ALU_32_Bit_Testbench $end
$var wire 32 ! result [31:0] $end
$var reg 16 " a [15:0] $end
$var reg 16 # b [15:0] $end
$var reg 4 $ op_select [3:0] $end
$upscope $end
$enddefinitions $end
$comment Show the parameter values. $end
$dumpall
$end
#0
$dumpvars
b0 $
b11 #
b101 "
b1000 !
$end
#10
b10 !
b1 $
#20
b1 !
b10 $
b1 #
b1111111111111111 "
#30
b1111000011110000 !
b11 $
b0 #
b1111000011110000 "
#40
b11111111111111111111111100000000 !
b100 $
b11111111 #
b1111111111111111 "
#50
b101 $
b0 "
#60
b1111111111111111 !
b110 $
b101010101010101 #
b1010101010101010 "
#70
b11111111111111110000000000000000 !
b111 $
